ctbl_cylon/__init__.py
ctbl_cylon/skin.py
ctbl_cylon-0.0.5.dist-info/METADATA
ctbl_cylon-0.0.5.dist-info/WHEEL
ctbl_cylon-0.0.5.dist-info/licenses/LICENSE
ctbl_cylon-0.0.5.dist-info/RECORD
