Metadata-Version: 2.3
Name: ctbl_cylon
Version: 0.0.5
Summary: A CLI command that automatizes the task of setting up accounts in new machines.
Author-email: Cristian Bravo Lillo <cristian.bravo@gmail.com>
License: MIT
Classifier: Development Status :: 2 - Pre-Alpha
Classifier: Environment :: Console
Classifier: License :: OSI Approved :: MIT License
Classifier: Operating System :: POSIX :: Linux
Classifier: Programming Language :: Python :: 3.8
Classifier: Topic :: Utilities
Requires-Python: >=3.8
